[
  {
    "video_id": "3260258075282189687",
    "videoDownloadUrl": "https://amazingmachine.github.io/nina/all_json/selected_pairs_1.json",
    "coverImgUrl": ""
  },
  {
    "video_id": "13549968-hd_1920_1080_60fps-r90_with_audio",
    "videoDownloadUrl": "https://amazingmachine.github.io/nina/all_json/selected_pairs_10.json",
    "coverImgUrl": ""
  },
  {
    "video_id": "3282433675324853428_62342143103",
    "videoDownloadUrl": "https://amazingmachine.github.io/nina/all_json/selected_pairs_11.json",
    "coverImgUrl": ""
  },
  {
    "video_id": "3254656052364857167",
    "videoDownloadUrl": "https://amazingmachine.github.io/nina/all_json/selected_pairs_12.json",
    "coverImgUrl": ""
  },
  {
    "video_id": "3256856700877321611",
    "videoDownloadUrl": "https://amazingmachine.github.io/nina/all_json/selected_pairs_13.json",
    "coverImgUrl": ""
  },
  {
    "video_id": "3270509984689512253",
    "videoDownloadUrl": "https://amazingmachine.github.io/nina/all_json/selected_pairs_14.json",
    "coverImgUrl": ""
  },
  {
    "video_id": "3214913489490974680",
    "videoDownloadUrl": "https://amazingmachine.github.io/nina/all_json/selected_pairs_15.json",
    "coverImgUrl": ""
  },
  {
    "video_id": "2605169088535882867_48204584147",
    "videoDownloadUrl": "https://amazingmachine.github.io/nina/all_json/selected_pairs_16.json",
    "coverImgUrl": ""
  },
  {
    "video_id": "3279126329530051765_63962285335",
    "videoDownloadUrl": "https://amazingmachine.github.io/nina/all_json/selected_pairs_17.json",
    "coverImgUrl": ""
  },
  {
    "video_id": "3287971224776720622_63962285335",
    "videoDownloadUrl": "https://amazingmachine.github.io/nina/all_json/selected_pairs_18.json",
    "coverImgUrl": ""
  },
  {
    "video_id": "3282976632364973060_63962285335",
    "videoDownloadUrl": "https://amazingmachine.github.io/nina/all_json/selected_pairs_19.json",
    "coverImgUrl": ""
  },
  {
    "video_id": "3289236787180111702_63962285335",
    "videoDownloadUrl": "https://amazingmachine.github.io/nina/all_json/selected_pairs_2.json",
    "coverImgUrl": ""
  },
  {
    "video_id": "3281682123375214013_63962285335",
    "videoDownloadUrl": "https://amazingmachine.github.io/nina/all_json/selected_pairs_20.json",
    "coverImgUrl": ""
  },
  {
    "video_id": "3281544175520162412_61271221291",
    "videoDownloadUrl": "https://amazingmachine.github.io/nina/all_json/selected_pairs_21.json",
    "coverImgUrl": ""
  },
  {
    "video_id": "3277168494684727303",
    "videoDownloadUrl": "https://amazingmachine.github.io/nina/all_json/selected_pairs_22.json",
    "coverImgUrl": ""
  },
  {
    "video_id": "3290898087410944117_63962285335",
    "videoDownloadUrl": "https://amazingmachine.github.io/nina/all_json/selected_pairs_23.json",
    "coverImgUrl": ""
  },
  {
    "video_id": "3283711133378670220_63962285335",
    "videoDownloadUrl": "https://amazingmachine.github.io/nina/all_json/selected_pairs_24.json",
    "coverImgUrl": ""
  },
  {
    "video_id": "3269087138064626367_61271221291",
    "videoDownloadUrl": "https://amazingmachine.github.io/nina/all_json/selected_pairs_25.json",
    "coverImgUrl": ""
  },
  {
    "video_id": "3279761119422051652",
    "videoDownloadUrl": "https://amazingmachine.github.io/nina/all_json/selected_pairs_26.json",
    "coverImgUrl": ""
  },
  {
    "video_id": "3227816962659277919",
    "videoDownloadUrl": "https://amazingmachine.github.io/nina/all_json/selected_pairs_27.json",
    "coverImgUrl": ""
  },
  {
    "video_id": "3235535885965756753_62342143103",
    "videoDownloadUrl": "https://amazingmachine.github.io/nina/all_json/selected_pairs_28.json",
    "coverImgUrl": ""
  },
  {
    "video_id": "3277843923204383291_63962285335",
    "videoDownloadUrl": "https://amazingmachine.github.io/nina/all_json/selected_pairs_29.json",
    "coverImgUrl": ""
  },
  {
    "video_id": "3254860189455019402_62342143103",
    "videoDownloadUrl": "https://amazingmachine.github.io/nina/all_json/selected_pairs_3.json",
    "coverImgUrl": ""
  },
  {
    "video_id": "932af9b3-e12f-45f8-a4da-803252551470_with_audio_hevc",
    "videoDownloadUrl": "https://amazingmachine.github.io/nina/all_json/selected_pairs_30.json",
    "coverImgUrl": ""
  },
  {
    "video_id": "3226164568624157103",
    "videoDownloadUrl": "https://amazingmachine.github.io/nina/all_json/selected_pairs_31.json",
    "coverImgUrl": ""
  },
  {
    "video_id": "3269619706132598339",
    "videoDownloadUrl": "https://amazingmachine.github.io/nina/all_json/selected_pairs_32.json",
    "coverImgUrl": ""
  },
  {
    "video_id": "3253095104280052180_61271221291",
    "videoDownloadUrl": "https://amazingmachine.github.io/nina/all_json/selected_pairs_33.json",
    "coverImgUrl": ""
  },
  {
    "video_id": "3238015451859175939",
    "videoDownloadUrl": "https://amazingmachine.github.io/nina/all_json/selected_pairs_34.json",
    "coverImgUrl": ""
  },
  {
    "video_id": "7912326-hd_1920_1080_30fps-r90_with_audio",
    "videoDownloadUrl": "https://amazingmachine.github.io/nina/all_json/selected_pairs_35.json",
    "coverImgUrl": ""
  },
  {
    "video_id": "3002601083792656549",
    "videoDownloadUrl": "https://amazingmachine.github.io/nina/all_json/selected_pairs_36.json",
    "coverImgUrl": ""
  },
  {
    "video_id": "3273341600078270533_61271221291",
    "videoDownloadUrl": "https://amazingmachine.github.io/nina/all_json/selected_pairs_37.json",
    "coverImgUrl": ""
  },
  {
    "video_id": "3263213392355371314_61271221291",
    "videoDownloadUrl": "https://amazingmachine.github.io/nina/all_json/selected_pairs_4.json",
    "coverImgUrl": ""
  },
  {
    "video_id": "3233704529703190619_62342143103",
    "videoDownloadUrl": "https://amazingmachine.github.io/nina/all_json/selected_pairs_5.json",
    "coverImgUrl": ""
  },
  {
    "video_id": "3250176060692024139_62342143103",
    "videoDownloadUrl": "https://amazingmachine.github.io/nina/all_json/selected_pairs_6.json",
    "coverImgUrl": ""
  },
  {
    "video_id": "3222542166119701122",
    "videoDownloadUrl": "https://amazingmachine.github.io/nina/all_json/selected_pairs_7.json",
    "coverImgUrl": ""
  },
  {
    "video_id": "3248103408624206344",
    "videoDownloadUrl": "https://amazingmachine.github.io/nina/all_json/selected_pairs_8.json",
    "coverImgUrl": ""
  },
  {
    "video_id": "10727237-hd_1920_1080_30fps-r90_with_audio",
    "videoDownloadUrl": "https://amazingmachine.github.io/nina/all_json/selected_pairs_9.json",
    "coverImgUrl": ""
  }
]